sifter_extensions/__init__.py
sifter_extensions/commands/__init__.py
sifter_extensions/commands/pipe.py
sifter_extensions/commands/rewrite.py
sifter3_extensions-0.0.1.dist-info/LICENSE.txt
sifter3_extensions-0.0.1.dist-info/METADATA
sifter3_extensions-0.0.1.dist-info/WHEEL
sifter3_extensions-0.0.1.dist-info/entry_points.txt
sifter3_extensions-0.0.1.dist-info/top_level.txt
sifter3_extensions-0.0.1.dist-info/RECORD
